[
  {
    "id": 1,
    "data": "2025-10-18",
    "hora": "15:00",
    "local": "Casa do João",
    "musicas": [
      { "nome": "Alvo Mais Que a Neve", "link": "https://www.youtube.com/watch?v=example" },
      { "nome": "Grandes Coisas", "link": "https://open.spotify.com/track/example" }
    ]
  },
  {
    "id": 2,
    "data": "2025-10-25",
    "hora": "14:00",
    "local": "Sede da Banda",
    "musicas": [
      { "nome": "Outra Música", "link": "https://www.youtube.com/watch?v=example3" }
    ]
  }
]
